vs_score/__init__.py
vs_score/feature_engineering.py
vs_score/merge_clean.py
vs_score/predict_api.py
vs_score/train_model.py
vs_score-0.1.0.dist-info/licenses/LICENSE
vs_score-0.1.0.dist-info/METADATA
vs_score-0.1.0.dist-info/WHEEL
vs_score-0.1.0.dist-info/top_level.txt
vs_score-0.1.0.dist-info/RECORD
