Metadata-Version: 2.4
Name: vs-score
Version: 0.1.0
Summary: A package for volleyball match outcome prediction and statistical analysis.
Author-email: irem <iremozluoglu@gmail.com>
License: MIT License
Project-URL: Homepage, https://github.com/iremozluoglu/vs-score
Keywords: volleyball,prediction,machine learning,fastapi
Classifier: Programming Language :: Python :: 3
Classifier: License :: OSI Approved :: MIT License
Classifier: Operating System :: OS Independent
Requires-Python: >=3.8
License-File: LICENSE
Dynamic: license-file
